CHANGELOG.txt
LICENCE.txt
MANIFEST.in
README.txt
setup.py
salihcancalculator/__init__.py
salihcancalculator/calculate.py
salihcancalculator.egg-info/PKG-INFO
salihcancalculator.egg-info/SOURCES.txt
salihcancalculator.egg-info/dependency_links.txt
salihcancalculator.egg-info/top_level.txt