Metadata-Version: 1.1
Name: salihcancalculator
Version: 0.0.1
Summary: A very basic calculator
Home-page: UNKNOWN
Author: Salih Can
Author-email: example@example.com
License: MIT
Keywords: calculator
Platform: UNKNOWN
Classifier: Development Status :: 5 - Production/Stable
Classifier: Intended Audience :: Education
Classifier: License :: OSI Approved :: MIT License
Classifier: Programming Language :: Python :: 3
